{
  "@type": "Recipe",
  "aggregateRating": {
    "@type": "AggregateRating",
    "ratingCount": "25",
    "ratingValue": "4.76"
  },
  "author": {
    "@type": "Person",
    "name": "Beth - Budget Bytes"
  },
  "cookTime": "PT25M",
  "createdAt": "2020-10-08T05:46:38.704Z",
  "datePublished": "2019-10-13T14:22:36+00:00",
  "description": "This super thick, warm, and comforting tomato soup has two secret ingredients that make it rich and delicious without any dairy. 100% vegan!",
  "image": [
    "https://www.budgetbytes.com/wp-content/uploads/2019/10/Secret-Ingredient-Tomato-Soup-bowl-overhead.jpg",
    "https://www.budgetbytes.com/wp-content/uploads/2019/10/Secret-Ingredient-Tomato-Soup-bowl-overhead-500x500.jpg",
    "https://www.budgetbytes.com/wp-content/uploads/2019/10/Secret-Ingredient-Tomato-Soup-bowl-overhead-500x375.jpg",
    "https://www.budgetbytes.com/wp-content/uploads/2019/10/Secret-Ingredient-Tomato-Soup-bowl-overhead-480x270.jpg"
  ],
  "keywords": "Easy Recipe, Vegan Soup",
  "name": "Secret Ingredient Tomato Soup",
  "nutrition": {
    "@type": "NutritionInformation",
    "calories": "278.48 kcal",
    "carbohydrateContent": "44.33 g",
    "fatContent": "7.25 g",
    "fiberContent": "10.78 g",
    "proteinContent": "10.13 g",
    "servingSize": "1.25 Cups",
    "sodiumContent": "1254.33 mg"
  },
  "prepTime": "PT5M",
  "recipeIngredient": [
    "2 Tbsp olive oil ($0.32)",
    "1 clove garlic, minced ($0.08)",
    "1/2 tsp dried oregano ($0.05)",
    "1/2 tsp dried basil ($0.05)",
    "1/4 tsp dried thyme ($0.03)",
    "1/4 tsp dried rosemary ($0.03)",
    "1 pinch crushed red pepper ($0.02)",
    "freshly cracked black pepper ($0.02)",
    "3 oz. tomato paste ($0.27)",
    "1 Tbsp brown sugar ($0.04)",
    "1 28oz. can crushed tomatoes ($0.89)",
    "2 cups vegetable broth ($0.26)",
    "1 15oz. can cannellini beans ($0.49)",
    "1 Tbsp nutritional yeast ($0.06)",
    "1/4 tsp salt, or to taste ($0.01)"
  ],
  "recipeInstructions": [
    {
      "@type": "HowToStep",
      "text": "Add the olive oil, minced garlic, oregano, basil, thyme, rosemary, crushed red pepper, and some freshly cracked black pepper (about 10 cranks of a pepper mill) to a soup pot. Cook and stir the herbs and oil over medium heat for about one minute, or until the garlic is soft and fragrant."
    },
    {
      "@type": "HowToStep",
      "text": "Add the tomato paste and brown sugar. Continue to stir and cook the tomato paste mixture over medium heat for 2-3 minutes."
    },
    {
      "@type": "HowToStep",
      "text": "Pour the crushed tomatoes and vegetable broth into the pot and stir to combine. As the soup begins to heat through, add a can of cannellini beans (with the liquid from the can) to a blender and purée until completely smooth. Pour the pouréed beans into the soup and stir to combine again."
    },
    {
      "@type": "HowToStep",
      "text": "Place a lid on the pot and allow it to come up to a simmer. Once simmering, turn the heat down to medium low and let it simmer, stirring occasionally, for 20 minutes."
    },
    {
      "@type": "HowToStep",
      "text": "After simmering for 20 minutes, add the nutritional yeast and stir to combine. Taste the soup and add salt to taste (about 1/4 tsp). Serve hot."
    }
  ],
  "recipeYield": "4",
  "sameAs": ["https://www.budgetbytes.com/secret-ingredient-tomato-soup/"],
  "totalTime": "PT30M",
  "updatedAt": "2020-10-08T05:46:38.704Z"
}
